{
    "fallow_control": {
        "proportion": 0.05,
        "labels": {
            "True": "No Ads",
            "False": "Ads"
        },
        "seed": 101
    },
    "macro_locations": {
        "HN": {
            "cells": [
                [0.05, "3: No Banner"],
                [0.2, "2: Random"],
                [1.0, "1: Personalised"]
            ],
            "seed": 201,
            "page": "/",
            "screen": "Home",
            "reported_value": "SessionRevenue"
        },
        "SB": {
            "cells": [
                [0.05, "3: No Banner"],
                [0.2, "2: Random"],
                [1.0, "1: Personalised"]
            ],
            "seed": 202,
            "page": "/shoppingbag",
            "screen": "Cart",
            "reported_value": "ProductRevenuePostFirstHit"
        },
        "OC": {
            "cells": [
                [0.05, "3: No Banner"],
                [0.2, "2: Random"],
                [1.0, "1: Personalised"]
            ],
            "seed": 203,
            "page": "%checkout/complete%",
		    "screen": "Checkout Completed",
            "reported_value": "ProductRevenuePostFirstHit"
        },
        "LP": {
            "cells": [
                [0.1, "3: No Banner"],
                [1.0, "2: Random"]
            ],
            "seed": 204,
            "page": "",
		    "screen": "",
            "reported_value": "SessionRevenue"
        },
        "PH": {
            "cells": [
                [0.05, "3: No Banner"],
                [0.2, "2: Random"],
                [1.0, "1: Personalised"]
            ],
            "seed": 205,
            "page": "/",
            "screen": "Home",
            "reported_value": "SessionRevenue"
        },
        "AdHocAB1": {
            "cells": [
                [0.5, "A"],
                [1.0, "B"]
            ],
            "seed": 301
        },
        "AdHocAB2": {
            "cells": [
                [0.5, "A"],
                [1.0, "B"]
            ],
            "seed": 302
        },
        "AdHocAB3": {
            "cells": [
                [0.5, "A"],
                [1.0, "B"]
            ],
            "seed": 303
        },
        "AdHocAB4": {
            "cells": [
                [0.5, "A"],
                [1.0, "B"]
            ],
            "seed": 304
        },
        "ChampionChallenger": {
            "cells": [
                [0.5, "Champion"],
                [1.0, "Challenger"]
            ],
            "seed": 401
        }
    },
    "divisions": {
        "Womens": {
            "model": "div_womens"
        },
        "Mens": {
            "model": "div_mens"
        },
        "Girls": {
            "model": "div_girls"
        },
        "Boys": {
            "model": "div_boys"
        },
        "Baby": {
            "model": "div_baby"
        },
        "Home": {
            "model": "div_home"
        },
        "Beauty": {
            "model": "div_beauty"
        }
    },
    "locations": {
        "HN1": {
            "map": [
                {
                    "when": [{"macro": "HN", "match": "3: No Banner"}],
                    "then": "Control"
                },
                {
                    "when": [{"macro": "HN", "match": "2. Random"}],
                    "then": "RandomAd"
                },
                {
                    "when": [{"macro": "HN", "match": "1: Personalised"}],
                    "then": "BestAd"
                },
                {
                    "when": [
                        {"macro": "HN", "match": "1: Personalised"},
                        {"macro": "ChampionChallenger", "match": "Challenger"}
                    ],
                    "then": "BestAd"
                }
            ]
        },
        "SB1": {
            "map": [
                {
                    "when": [{"macro": "SB", "match": "3: No Banner"}],
                    "then": "Control"
                },
                {
                    "when": [{"macro": "SB", "match": "2. Random"}],
                    "then": "RandomAd"
                },
                {
                    "when": [{"macro": "SB", "match": "1: Personalised"}],
                    "then": "BestAd"
                },
                {
                    "when": [
                        {"macro": "HN", "match": "1: Personalised"},
                        {"macro": "ChampionChallenger", "match": "Challenger"}
                    ],
                    "then": "BestChallengerAd"
                },
                {
                    "when": [{"macro": "AdHocAB1", "match": "B"}],
                    "then": "Control"
                }
            ]
        },
        "SB2": {
            "map": [
                {
                    "when": [{"macro": "SB", "match": "3: No Banner"}],
                    "then": "Control"
                },
                {
                    "when": [{"macro": "SB", "match": "2. Random"}],
                    "then": "RandomAd"
                },
                {
                    "when": [{"macro": "SB", "match": "1: Personalised"}],
                    "then": "BestAd"
                },
                {
                    "when": [
                        {"macro": "HN", "match": "1: Personalised"},
                        {"macro": "ChampionChallenger", "match": "Challenger"}
                    ],
                    "then": "BestChallengerAd"
                },
                {
                    "when": [{"macro": "AdHocAB2", "match": "B"}],
                    "then": "Control"
                }
            ]
        },
        "OC1": {
            "map": [
                {
                    "when": [{"macro": "OC", "match": "3: No Banner"}],
                    "then": "Control"
                },
                {
                    "when": [{"macro": "OC", "match": "2. Random"}],
                    "then": "RandomAd"
                },
                {
                    "when": [{"macro": "OC", "match": "1: Personalised"}],
                    "then": "BestAd"
                },
                {
                    "when": [
                        {"macro": "HN", "match": "1: Personalised"},
                        {"macro": "ChampionChallenger", "match": "Challenger"}
                    ],
                    "then": "BestChallengerAd"
                }
            ]
        },
        "LP1": {},
        "LP2": {},
        "LP3": {},
        "LP4": {},
        "LP5": {},
        "LP6": {},
        "LP7": {},
        "LP8": {},
        "LP9": {},
        "LP10": {},
        "LP11": {},
        "PH2": {
            "map": [
                {
                    "when": [{"macro": "PH", "match": "3: No Banner"}],
                    "then": "Control"
                },
                {
                    "when": [{"macro": "PH", "match": "2. Random"}],
                    "then": "RandomAd"
                },
                {
                    "when": [{"macro": "PH", "match": "1: Personalised"}],
                    "then": "BestAd"
                },
                {
                    "when": [
                        {"macro": "HN", "match": "1: Personalised"},
                        {"macro": "ChampionChallenger", "match": "Challenger"}
                    ],
                    "then": "BestChallengerAd"
                }
            ],
            "best_args": {
                "return_ranks": [1]
            }
        },
        "PH3": {
            "map": [
                {
                    "when": [{"macro": "PH", "match": "3: No Banner"}],
                    "then": "Control"
                },
                {
                    "when": [{"macro": "PH", "match": "2. Random"}],
                    "then": "RandomAd"
                },
                {
                    "when": [{"macro": "PH", "match": "1: Personalised"}],
                    "then": "BestAd"
                },
                {
                    "when": [
                        {"macro": "HN", "match": "1: Personalised"},
                        {"macro": "ChampionChallenger", "match": "Challenger"}
                    ],
                    "then": "BestChallengerAd"
                }
            ],
            "best_args": {
                "return_ranks": [2]
            }
        },
        "PH4": {
            "map": [
                {
                    "when": [{"macro": "PH", "match": "3: No Banner"}],
                    "then": "Control"
                },
                {
                    "when": [{"macro": "PH", "match": "2. Random"}],
                    "then": "RandomAd"
                },
                {
                    "when": [{"macro": "PH", "match": "1: Personalised"}],
                    "then": "BestAd"
                },
                {
                    "when": [
                        {"macro": "HN", "match": "1: Personalised"},
                        {"macro": "ChampionChallenger", "match": "Challenger"}
                    ],
                    "then": "BestChallengerAd"
                }
            ],
            "best_args": {
                "return_ranks": [3]
            }
        },
        "PH5": {
            "map": [
                {
                    "when": [{"macro": "PH", "match": "3: No Banner"}],
                    "then": "Control"
                },
                {
                    "when": [{"macro": "PH", "match": "2. Random"}],
                    "then": "RandomAd"
                },
                {
                    "when": [{"macro": "PH", "match": "1: Personalised"}],
                    "then": "BestAd"
                },
                {
                    "when": [
                        {"macro": "HN", "match": "1: Personalised"},
                        {"macro": "ChampionChallenger", "match": "Challenger"}
                    ],
                    "then": "BestChallengerAd"
                }
            ],
            "best_args": {
                "return_ranks": [4]
            }
        }
    }
}